LICENSE
LICENSE.txt
MANIFEST.in
README.txt
setup.cfg
setup.py
ez_modern_treasury.egg-info/PKG-INFO
ez_modern_treasury.egg-info/SOURCES.txt
ez_modern_treasury.egg-info/dependency_links.txt
ez_modern_treasury.egg-info/requires.txt
ez_modern_treasury.egg-info/top_level.txt
modern_treasury/__init__.py
modern_treasury/auth.py
modern_treasury/modern_treasury.py
modern_treasury/objects/__init__.py
modern_treasury/objects/exceptions.py
modern_treasury/objects/reference_number.py
modern_treasury/objects/shared.py
modern_treasury/objects/request/__init__.py
modern_treasury/objects/request/account.py
modern_treasury/objects/request/account_details.py
modern_treasury/objects/request/address.py
modern_treasury/objects/request/counterparty.py
modern_treasury/objects/request/expected_payment.py
modern_treasury/objects/request/external_account.py
modern_treasury/objects/request/incoming_payment_detail.py
modern_treasury/objects/request/internal_account.py
modern_treasury/objects/request/line_item.py
modern_treasury/objects/request/payment_order.py
modern_treasury/objects/request/routing_details.py
modern_treasury/objects/request/transaction.py
modern_treasury/objects/request/virtual_account.py
modern_treasury/objects/response/__init__.py
modern_treasury/objects/response/account.py
modern_treasury/objects/response/account_details.py
modern_treasury/objects/response/address.py
modern_treasury/objects/response/connection.py
modern_treasury/objects/response/counterparty.py
modern_treasury/objects/response/expected_payment.py
modern_treasury/objects/response/external_account.py
modern_treasury/objects/response/incoming_payment_detail.py
modern_treasury/objects/response/internal_account.py
modern_treasury/objects/response/payment_order.py
modern_treasury/objects/response/routing_details.py
modern_treasury/objects/response/transaction.py
modern_treasury/objects/response/virtual_account.py
modern_treasury/objects/webhook_events/__init__.py
modern_treasury/objects/webhook_events/base.py
modern_treasury/objects/webhook_events/incoming_payment_detail_event.py
modern_treasury/objects/webhook_events/payment_order_event.py